terraform_parser/__init__.py
terraform_parser/functions.py
terraform_parser/keywords.py
terraform_parser/utils.py
terraform_parser-0.580.24088.dist-info/LICENSE
terraform_parser-0.580.24088.dist-info/METADATA
terraform_parser-0.580.24088.dist-info/WHEEL
terraform_parser-0.580.24088.dist-info/top_level.txt
terraform_parser-0.580.24088.dist-info/RECORD
