Metadata-Version: 2.1
Name: terraform-parser
Version: 0.580.24088
Summary: Terraform Parser - Parse Terraform to JSON
Home-page: https://github.com/klahnakoski/terraform-parser
Author: Kyle Lahnakoski
Author-email: kyle@lahnakoski.com
License: MPL 2.0
Classifier: Development Status :: 2 - Pre-Alpha
Classifier: Topic :: Software Development :: Libraries
Classifier: Topic :: Software Development :: Libraries :: Python Modules
Classifier: License :: OSI Approved :: Mozilla Public License 2.0 (MPL 2.0)
Classifier: Programming Language :: Python :: 3.8
Classifier: Programming Language :: Python :: 3.9
Classifier: Programming Language :: Python :: 3.10
Classifier: Programming Language :: Python :: 3.11
Classifier: Programming Language :: Python :: 3.12
License-File: LICENSE
Requires-Dist: diagrams
Requires-Dist: mo-dots ==9.578.24081
Requires-Dist: mo-imports ==7.546.24057
Requires-Dist: mo-parsing ==8.580.24088
Requires-Dist: mo-streams ==1.579.24081
Provides-Extra: tests
Requires-Dist: mo-testing ; extra == 'tests'
Requires-Dist: mo-files ; extra == 'tests'
Requires-Dist: mo-streams ; extra == 'tests'
